img3d/__init__.py
img3d/image_transformer.py
img3d-1.0.1.dist-info/LICENSE.txt
img3d-1.0.1.dist-info/METADATA
img3d-1.0.1.dist-info/WHEEL
img3d-1.0.1.dist-info/top_level.txt
img3d-1.0.1.dist-info/RECORD
