Metadata-Version: 2.2
Name: img3d
Version: 1.0.1
Summary: A Python Library for 3D Image Transformation.
Home-page: https://github.com/OmidAlekasir/image_transformer
Author: Majid Alekasir
Author-email: <majid.alekasir@gmail.com>
Keywords: python,image,transformation,translation,rotation,homography,3D,spherical,roll,pitch,yaw,stabilization,coordinates
Classifier: Development Status :: 5 - Production/Stable
Classifier: Intended Audience :: Developers
Classifier: Programming Language :: Python :: 3.10
Classifier: Operating System :: Unix
Classifier: Operating System :: MacOS :: MacOS X
License-File: LICENSE.txt
Dynamic: author
Dynamic: author-email
Dynamic: classifier
Dynamic: description
Dynamic: description-content-type
Dynamic: home-page
Dynamic: keywords
Dynamic: summary
